worktree_manager/__init__.py
worktree_manager/config.py
worktree_manager/manager.py
worktree_manager/utils.py
worktree_manager-0.1.8.dist-info/entry_points.txt
worktree_manager-0.1.8.dist-info/WHEEL
worktree_manager-0.1.8.dist-info/METADATA
worktree_manager-0.1.8.dist-info/RECORD
